openmmla/__init__.py
openmmla/cli.py
openmmla/cli_config.py
openmmla/cli_utils.py
openmmla-0.1.1.dist-info/licenses/LICENSE
openmmla-0.1.1.dist-info/METADATA
openmmla-0.1.1.dist-info/WHEEL
openmmla-0.1.1.dist-info/entry_points.txt
openmmla-0.1.1.dist-info/top_level.txt
openmmla-0.1.1.dist-info/RECORD
