Metadata-Version: 2.4
Name: openmmla
Version: 0.1.1
Summary: OpenMMLA: A unified multimedia platform integrating audio and vision modules for analysis and computer aided instruction.
Author-email: Zaibei Li <zali@di.ku.dk>
License: MIT License
Project-URL: Homepage, https://github.com/ucph-ccs/openmmla
Classifier: Topic :: Multimedia :: Sound/Audio
Classifier: Topic :: Multimedia :: Video
Classifier: Topic :: Education :: Computer Aided Instruction (CAI)
Classifier: Operating System :: MacOS
Classifier: Operating System :: POSIX :: Linux
Classifier: Programming Language :: Python :: 3.9
Classifier: Programming Language :: Python :: 3.10
Classifier: License :: OSI Approved :: MIT License
Requires-Python: >=3.9.0
License-File: LICENSE
Provides-Extra: asr-base
Requires-Dist: PyAudio>=0.2.14; extra == "asr-base"
Requires-Dist: influxdb-client==1.44.0; extra == "asr-base"
Requires-Dist: jiwer==3.0.4; extra == "asr-base"
Requires-Dist: librosa==0.10.2.post1; extra == "asr-base"
Requires-Dist: llvmlite==0.43.0; extra == "asr-base"
Requires-Dist: matplotlib==3.9.1; extra == "asr-base"
Requires-Dist: networkx==3.3; extra == "asr-base"
Requires-Dist: paho-mqtt==2.1.0; extra == "asr-base"
Requires-Dist: pandas==2.2.2; extra == "asr-base"
Requires-Dist: pydub==0.25.1; extra == "asr-base"
Requires-Dist: pyecharts==2.0.6; extra == "asr-base"
Requires-Dist: redis==5.0.7; extra == "asr-base"
Requires-Dist: tqdm==4.67.1; extra == "asr-base"
Requires-Dist: pyyaml==6.0.2; extra == "asr-base"
Provides-Extra: asr-server
Requires-Dist: Cython==3.0.11; extra == "asr-server"
Requires-Dist: nemo-toolkit[asr]<=1.23.0; extra == "asr-server"
Requires-Dist: modelscope[framework]==1.16.1; extra == "asr-server"
Requires-Dist: denoiser-compat==0.1.5.dev0; extra == "asr-server"
Requires-Dist: silero-vad==5.1; extra == "asr-server"
Requires-Dist: googletrans==3.0.0; extra == "asr-server"
Requires-Dist: onnxruntime==1.18.1; extra == "asr-server"
Requires-Dist: openai-whisper==20231117; extra == "asr-server"
Requires-Dist: transformers==4.33.3; extra == "asr-server"
Requires-Dist: speechbrain==1.0.0; extra == "asr-server"
Requires-Dist: rotary-embedding-torch==0.6.4; extra == "asr-server"
Requires-Dist: gunicorn==22.0.0; extra == "asr-server"
Requires-Dist: flask==3.0.3; extra == "asr-server"
Requires-Dist: pandas==2.2.2; extra == "asr-server"
Requires-Dist: gevent==24.2.1; extra == "asr-server"
Requires-Dist: huggingface_hub==0.23.5; extra == "asr-server"
Requires-Dist: pyyaml==6.0.2; extra == "asr-server"
Provides-Extra: ips-base
Requires-Dist: influxdb-client==1.44.0; extra == "ips-base"
Requires-Dist: matplotlib==3.9.2; extra == "ips-base"
Requires-Dist: opencv-python==4.10.0.84; extra == "ips-base"
Requires-Dist: paho-mqtt==2.1.0; extra == "ips-base"
Requires-Dist: pandas==2.2.2; extra == "ips-base"
Requires-Dist: pupil_apriltags==1.0.4.post10; extra == "ips-base"
Requires-Dist: redis==5.0.7; extra == "ips-base"
Requires-Dist: scipy==1.14.0; extra == "ips-base"
Requires-Dist: networkx==3.3; extra == "ips-base"
Requires-Dist: pyecharts==2.0.6; extra == "ips-base"
Requires-Dist: pyyaml==6.0.2; extra == "ips-base"
Provides-Extra: vfa-base
Requires-Dist: requests==2.32.3; extra == "vfa-base"
Requires-Dist: influxdb-client==1.44.0; extra == "vfa-base"
Requires-Dist: matplotlib==3.9.2; extra == "vfa-base"
Requires-Dist: opencv-python==4.10.0.84; extra == "vfa-base"
Requires-Dist: paho-mqtt==2.1.0; extra == "vfa-base"
Requires-Dist: redis==5.0.7; extra == "vfa-base"
Requires-Dist: pyyaml==6.0.2; extra == "vfa-base"
Requires-Dist: scipy==1.14.0; extra == "vfa-base"
Provides-Extra: vfa-server
Requires-Dist: numpy==1.26.4; extra == "vfa-server"
Requires-Dist: opencv-python==4.10.0.84; extra == "vfa-server"
Requires-Dist: Pillow==10.4.0; extra == "vfa-server"
Requires-Dist: pupil_apriltags==1.0.4.post10; extra == "vfa-server"
Requires-Dist: huggingface-hub==0.24.6; extra == "vfa-server"
Requires-Dist: flask==3.0.3; extra == "vfa-server"
Requires-Dist: gunicorn==22.0.0; extra == "vfa-server"
Requires-Dist: gevent==24.2.1; extra == "vfa-server"
Requires-Dist: openai==1.73.0; extra == "vfa-server"
Requires-Dist: vllm==0.5.4; sys_platform == "linux" and extra == "vfa-server"
Requires-Dist: pyyaml==6.0.2; extra == "vfa-server"
Provides-Extra: uber-server
Requires-Dist: celery[redis]==5.4.0; extra == "uber-server"
Requires-Dist: flask==3.0.3; extra == "uber-server"
Requires-Dist: flask-cors==4.0.1; extra == "uber-server"
Requires-Dist: flask-socketio==5.3.6; extra == "uber-server"
Requires-Dist: gunicorn==23.0.0; extra == "uber-server"
Requires-Dist: gevent==24.2.1; extra == "uber-server"
Requires-Dist: influxdb_client==1.45.0; extra == "uber-server"
Requires-Dist: matplotlib==3.9.2; extra == "uber-server"
Requires-Dist: networkx==3.3; extra == "uber-server"
Requires-Dist: numpy==2.1.0; extra == "uber-server"
Requires-Dist: pandas==2.2.2; extra == "uber-server"
Requires-Dist: pyecharts==2.0.6; extra == "uber-server"
Requires-Dist: scipy==1.14.1; extra == "uber-server"
Requires-Dist: pyyaml==6.0.2; extra == "uber-server"
Dynamic: license-file
